zooper_common/ai.py
zooper_common/ai_finetuner.py
zooper_common/s3.py
zooper_common-0.1.52.dist-info/LICENSE
zooper_common-0.1.52.dist-info/METADATA
zooper_common-0.1.52.dist-info/WHEEL
zooper_common-0.1.52.dist-info/top_level.txt
zooper_common-0.1.52.dist-info/RECORD
